deepcohort/__init__.py
deepcohort/src/__init__.py
deepcohort/src/tree_cohort.py
deepcohort-0.0.1.dist-info/LICENSE
deepcohort-0.0.1.dist-info/METADATA
deepcohort-0.0.1.dist-info/WHEEL
deepcohort-0.0.1.dist-info/top_level.txt
deepcohort-0.0.1.dist-info/RECORD
