Metadata-Version: 2.1
Name: deepcohort
Version: 0.0.1
Summary: Cohort formation based on Automated Data Slicing
Home-page: https://github.com/lakshyakh93/deepcohort
Author: Lakshya Khandelwal
Author-email: lakshaya.khandelwal@gmail.com
License: UNKNOWN
Platform: UNKNOWN
Classifier: Programming Language :: Python :: 3
Classifier: License :: OSI Approved :: MIT License
Classifier: Operating System :: OS Independent
License-File: LICENSE
Requires-Dist: pandas
Requires-Dist: sklearn
Requires-Dist: matplotlib
Requires-Dist: tqdm
Requires-Dist: dtreeviz
